np_envs-0.1.6.dist-info/METADATA
np_envs-0.1.6.dist-info/WHEEL
np_envs-0.1.6.dist-info/entry_points.txt
np_envs/__init__.py
np_envs/__main__.py
np_envs/assets/activate_this.py
np_envs/assets/example-pip.ini
np_envs/config.py
np_envs/env.py
np_envs-0.1.6.dist-info/RECORD
