Metadata-Version: 2.1
Name: np-envs
Version: 0.1.6
Summary: Config and scripts for managing virtual envs for Mindscope Neuropixels projects.
Author-Email: bjhardcastle <ben.hardcastle@alleninstitute.org>
License: MIT
Requires-Python: >=3.8
Requires-Dist: np-config>=0.4.20
Requires-Dist: np-logging>=0.5.1
Requires-Dist: np-tools>=0.1.14
Requires-Dist: importlib-resources>=5.12.0
Requires-Dist: typer>=0.9.0
